steamguard/__init__.py
steamguard/api.py
steamguard/exceptions.py
steamguard/mobile.py
steamguard/steam_api_mobile.py
steamguard/steam_api_web.py
steamguard/steam_session.py
steamguard-1.0.6.dist-info/LICENSE
steamguard-1.0.6.dist-info/METADATA
steamguard-1.0.6.dist-info/WHEEL
steamguard-1.0.6.dist-info/top_level.txt
steamguard-1.0.6.dist-info/RECORD
