Metadata-Version: 2.1
Name: steamguard
Version: 1.0.6
Summary: Simple Python module to add a phone number to your steam account and enable mobile authentication. It also generates Steam Guard codes, send and confirm tradeoffer and much more!
Home-page: https://github.com/th3poli/steamguard
Author: th3poli
Author-email: 
License: MIT
Keywords: steam,mobile,auth,guard,steamcommunity,tradeoffer
License-File: LICENSE
Requires-Dist: requests
Requires-Dist: rsa
Requires-Dist: beautifulsoup4
